nonebot_plugin_abstract/__init__.py
nonebot_plugin_abstract/data.py
nonebot_plugin_abstract/emoji.py
nonebot_plugin_abstract-1.0.6.dist-info/LICENSE
nonebot_plugin_abstract-1.0.6.dist-info/METADATA
nonebot_plugin_abstract-1.0.6.dist-info/WHEEL
nonebot_plugin_abstract-1.0.6.dist-info/RECORD
