Metadata-Version: 2.1
Name: nonebot-plugin-abstract
Version: 1.0.6
Summary: Plugin for nonebot2 that abstracts statements
Home-page: https://github.com/CherryCherries/nonebot-plugin-abstract
License: MIT
Author: CherryCherries
Author-email: cherrycherries@foxmail.com
Requires-Python: >=3.7.3,<4.0.0
Classifier: License :: OSI Approved :: MIT License
Classifier: Programming Language :: Python :: 3
Classifier: Programming Language :: Python :: 3.8
Classifier: Programming Language :: Python :: 3.9
Classifier: Programming Language :: Python :: 3.10
Classifier: Programming Language :: Python :: 3.11
Requires-Dist: jieba (==0.42.1)
Requires-Dist: nonebot-adapter-onebot (>=2.0.0-beta.1,<3.0.0)
Requires-Dist: nonebot2 (>=2.0.0-beta.1,<3.0.0)
Requires-Dist: pinyin (==0.4.0)
Project-URL: Repository, https://github.com/CherryCherries/nonebot-plugin-abstract
